LICENSE
MANIFEST.in
README.md
pyproject.toml
setup.cfg
setup.py
django_dynamic_contents.egg-info/PKG-INFO
django_dynamic_contents.egg-info/SOURCES.txt
django_dynamic_contents.egg-info/dependency_links.txt
django_dynamic_contents.egg-info/requires.txt
django_dynamic_contents.egg-info/top_level.txt
dynamic_contents/__init__.py
dynamic_contents/admin.py
dynamic_contents/apps.py
dynamic_contents/gateway.py
dynamic_contents/models.py
dynamic_contents/pagination.py
dynamic_contents/serializers.py
dynamic_contents/settings.py
dynamic_contents/translation.py
dynamic_contents/urls.py
dynamic_contents/utils.py
dynamic_contents/views.py
dynamic_contents/tests/__init__.py
dynamic_contents/tests/test_utils.py