Metadata-Version: 2.1
Name: django-dynamic-contents
Version: 1.0.37
Summary: A Django library for creating and managing dynamic, customizable content structures with ease. Designed to enhance multilingual support in Django applications, it facilitates the creation of HTML or text content that can be easily translated into multiple languages, offering a flexible solution for integrating varied content parts.
Home-page: https://github.com/runners-2022/django-dynamic-content
Author: Sunwook Kim
Author-email: sun@runners.im
License: MIT
Classifier: Environment :: Web Environment
Classifier: Framework :: Django
Classifier: Intended Audience :: Developers
Classifier: License :: OSI Approved :: BSD License
Classifier: Operating System :: OS Independent
Classifier: Programming Language :: Python
Classifier: Programming Language :: Python :: 3
Classifier: Programming Language :: Python :: 3.8
Classifier: Topic :: Internet :: WWW/HTTP
Classifier: Topic :: Internet :: WWW/HTTP :: Dynamic Content
Requires-Python: >=3.8
License-File: LICENSE
